compas_lcmtypes/__init__.py
compas_lcmtypes/bot_core/__init__.py
compas_lcmtypes/bot_core/image_metadata_t.py
compas_lcmtypes/bot_core/image_sync_t.py
compas_lcmtypes/bot_core/image_t.py
compas_lcmtypes/geometry/__init__.py
compas_lcmtypes/geometry/point_t.py
compas_lcmtypes/geometry/pose_t.py
compas_lcmtypes/geometry/pose_with_covariance_t.py
compas_lcmtypes/geometry/quaternion_t.py
compas_lcmtypes/geometry/transform_t.py
compas_lcmtypes/geometry/twist_t.py
compas_lcmtypes/geometry/twist_with_covariance_t.py
compas_lcmtypes/geometry/vector3_t.py
compas_lcmtypes/navlcm/__init__.py
compas_lcmtypes/navlcm/odometry_t.py
compas_lcmtypes/navlcm/pose_t.py
compas_lcmtypes/navlcm/position_t.py
compas_lcmtypes/navlcm/twist_t.py
compas_lcmtypes/navlcm/uuv_state_t.py
compas_lcmtypes/senlcm/__init__.py
compas_lcmtypes/senlcm/battery_t.py
compas_lcmtypes/senlcm/cmd_list_t.py
compas_lcmtypes/senlcm/ctd_t.py
compas_lcmtypes/senlcm/depth_t.py
compas_lcmtypes/senlcm/dvl_t.py
compas_lcmtypes/senlcm/effort_cmd_t.py
compas_lcmtypes/senlcm/gamepad_t.py
compas_lcmtypes/senlcm/generic_t.py
compas_lcmtypes/senlcm/gps_fix_t.py
compas_lcmtypes/senlcm/imu_t.py
compas_lcmtypes/senlcm/magnetometer_t.py
compas_lcmtypes/senlcm/multibeam_t.py
compas_lcmtypes/senlcm/rph_angrate_t.py
compas_lcmtypes/senlcm/rph_t.py
compas_lcmtypes/senlcm/sig_bool_t.py
compas_lcmtypes/senlcm/sig_double_t.py
compas_lcmtypes/senlcm/sig_long_t.py
compas_lcmtypes/standard/__init__.py
compas_lcmtypes/standard/header_t.py
compas_lcmtypes-2023.2.dist-info/WHEEL
compas_lcmtypes-2023.2.dist-info/METADATA
compas_lcmtypes-2023.2.dist-info/RECORD
