Metadata-Version: 2.1
Name: compas-lcmtypes
Version: 2023.2
Summary: CoMPAS LCM types
Author: Kevin Barnard
Author-email: kbarnard@mbari.org
Requires-Python: >=3.8,<4.0
Classifier: Programming Language :: Python :: 3
Classifier: Programming Language :: Python :: 3.8
Classifier: Programming Language :: Python :: 3.9
Classifier: Programming Language :: Python :: 3.10
Classifier: Programming Language :: Python :: 3.11
